setup.py
aioworkers_ipc/__init__.py
aioworkers_ipc/queue.py
aioworkers_ipc.egg-info/PKG-INFO
aioworkers_ipc.egg-info/SOURCES.txt
aioworkers_ipc.egg-info/dependency_links.txt
aioworkers_ipc.egg-info/requires.txt
aioworkers_ipc.egg-info/top_level.txt