Metadata-Version: 1.1
Name: aioworkers-ipc
Version: 0.0.1
Summary: Module for working with ipc
Home-page: https://github.com/aioworkers/aioworkers-ipc
Author: Alexander Malev
Author-email: yttrium@somedev.ru
License: Apache Software License 2.0
Keywords: aioworkers posix ipc
Platform: UNKNOWN
Classifier: Development Status :: 2 - Pre-Alpha
Classifier: Intended Audience :: Developers
Classifier: License :: OSI Approved :: Apache Software License
Classifier: Programming Language :: Python :: 3
Classifier: Programming Language :: Python :: 3.5
Classifier: Programming Language :: Python :: 3.6
